{"tick": 97, "scoreboard": [{"rank": 1, "team_id": 19, "services": [{"m": "Flagstore 1 (not checked)\n", "c": -1, "dc": [-1, -1, -1], "o": 1292.1263682293973, "do": 5.283420846742956, "d": 65.16268346811296, "dd": 2.0357142857142847, "s": 141.0, "ds": 0.0, "cap": 676, "dcap": 3, "st": 440, "dst": 0}, {"m": "Flagstore 1 (not checked)\n", "c": -1, "dc": [-1, 0, 2], "o": 507.7462482250545, "do": 0.0, "d": 85.94912176336541, "dd": 2.0396930655551415, "s": 201.0, "ds": 0.0, "cap": 263, "dcap": 0, "st": 137, "dst": 0}, {"m": "Flagstore 1 (up)\n", "c": 0, "dc": [2, 2, 0], "o": 1548.3892126051223, "do": 5.704786620530513, "d": 97.87475423252592, "dd": 2.037037037037038, "s": 108.0, "ds": 3.0, "cap": 803, "dcap": 3, "st": 18, "dst": 0}, {"m": "Flagstore 1 (faulty) - checking service: Unhandled error at check service.\n", "c": 2, "dc": [4, 4, 2], "o": 1994.652248136331, "do": 4.099636503442753, "d": 40.71035517052252, "dd": 0.0, "s": 61.5, "ds": 0.0, "cap": 826, "dcap": 2, "st": 280, "dst": 10}, {"m": "Flagstore 1 (not checked)\n", "c": -1, "dc": [-1, -1, -1], "o": 437.6892903232869, "do": 7.87024221453288, "d": 89.48237950664863, "dd": 2.0344827586206833, "s": 3.0, "ds": 0.0, "cap": 179, "dcap": 3, "st": 2, "dst": 0}, {"m": "Flagstore 1 (faulty) - placing flag: We cannot put the flag!!\n", "c": 2, "dc": [2, 2, 2], "o": 436.9118842326455, "do": 5.730287167657423, "d": 30.485308326229053, "dd": 0.0, "s": 165.0, "ds": 0.0, "cap": 226, "dcap": 3, "st": 221, "dst": 0}], "points": 7306.679854219242, "o": 6217.515251751837, "do": 28.688373352906524, "d": 409.6646024674045, "dd": 8.146927146927148, "s": 679.5, "ds": 3.0}, {"rank": 2, "team_id": 28, "services": [{"m": "Flagstore 1 (faulty) - placing flag: We cannot put the flag!!\n", "c": 2, "dc": [2, 2, 2], "o": 619.7996925191325, "do": 0.0, "d": 26.40056022408964, "dd": 0.0, "s": 90.0, "ds": 0.0, "cap": 337, "dcap": 0, "st": 410, "dst": 0}, {"m": "Flagstore 1 (faulty) - placing flag: list index out of range\n", "c": 2, "dc": [2, 2, 2], "o": 1816.3810267058973, "do": 0.0, "d": 86.27352395047409, "dd": 0.0, "s": 186.0, "ds": 0.0, "cap": 925, "dcap": 0, "st": 39, "dst": 0}, {"m": "Flagstore 1 (faulty) - placing flag: Got EOF while expecting output: \"Operation:\"\n", "c": 2, "dc": [0, 0, 2], "o": 1052.9448512645554, "do": 5.817704728950503, "d": 38.95870531008102, "dd": 0.0, "s": 81.0, "ds": 0.0, "cap": 543, "dcap": 3, "st": 131, "dst": 0}, {"m": "Flagstore 1 (faulty) - checking flag: Could not connect to service for getflag\n", "c": 2, "dc": [2, 4, 4], "o": 695.1098577220552, "do": 6.22316591520746, "d": 91.71307302491559, "dd": 0.0, "s": 132.0, "ds": 0.0, "cap": 320, "dcap": 3, "st": 113, "dst": 2}, {"m": "Flagstore 1 (up)\n", "c": 0, "dc": [0, 0, 2], "o": 1198.4520024669687, "do": 2.4162629757786362, "d": 69.25097561002453, "dd": 0.0, "s": 69.0, "ds": 3.0, "cap": 484, "dcap": 1, "st": 114, "dst": 2}, {"m": "Flagstore 1 (up)\n", "c": 0, "dc": [0, 0, 0], "o": 0.0, "do": 0.0, "d": 143.2406256877385, "dd": 2.0344827586206975, "s": 174.0, "ds": 3.0, "cap": 0, "dcap": 0, "st": 0, "dst": 0}], "points": 6570.524894485933, "o": 5382.6874306786085, "do": 14.457133619936599, "d": 455.83746380732333, "dd": 2.0344827586206975, "s": 732.0, "ds": 6.0}, {"rank": 3, "team_id": 16, "services": [{"m": "Flagstore 1 (faulty) - checking service: Checker detects that LFD file can not be accesed!\n", "c": 2, "dc": [2, 2, 2], "o": 1394.680101604725, "do": 12.419242234121384, "d": 38.657280003788955, "dd": 0.0, "s": 30.0, "ds": 0.0, "cap": 722, "dcap": 6, "st": 66, "dst": 0}, {"m": "Flagstore 1 (faulty) - placing flag: list index out of range\n", "c": 2, "dc": [2, 0, 2], "o": 185.84381176301585, "do": 9.95554457076949, "d": 48.9002138645433, "dd": 0.0, "s": 150.0, "ds": 0.0, "cap": 95, "dcap": 4, "st": 268, "dst": 0}, {"m": "Flagstore 1 (faulty) - placing flag: Got EOF while expecting output: \"Operation:\"\n", "c": 2, "dc": [2, 2, 2], "o": 1785.1092921946897, "do": 15.167993079584676, "d": 65.3651639938129, "dd": 0.0, "s": 129.0, "ds": 0.0, "cap": 910, "dcap": 7, "st": 418, "dst": 0}, {"m": "Flagstore 1 (flag not found) - checking flag: flag not found / not matching\n", "c": 3, "dc": [2, 4, 2], "o": 141.27558107021775, "do": 6.288217818321613, "d": 101.67492952038883, "dd": 0.0, "s": 138.0, "ds": 0.0, "cap": 69, "dcap": 3, "st": 78, "dst": 0}, {"m": "Flagstore 1 (faulty) - placing flag: We cannot put the flag!!\n", "c": 2, "dc": [2, 0, 2], "o": 293.33833415719226, "do": 2.5, "d": 83.42643130519103, "dd": 0.0, "s": 60.0, "ds": 0.0, "cap": 133, "dcap": 1, "st": 23, "dst": 0}, {"m": "Flagstore 1 (faulty) - placing flag: HTTPSConnectionPool(host='172.16.16.5', port=443):\n", "c": 2, "dc": [2, 0, 2], "o": 1536.3959003702955, "do": 4.8408775000471, "d": 32.56779497764018, "dd": 0.0, "s": 147.0, "ds": 0.0, "cap": 736, "dcap": 2, "st": 285, "dst": 0}], "points": 6361.234834825502, "o": 5336.643021160136, "do": 51.17187520284426, "d": 370.59181366536524, "dd": 0.0, "s": 654.0, "ds": 0.0}, {"rank": 4, "team_id": 23, "services": [{"m": "Flagstore 1 (not checked)\n", "c": -1, "dc": [-1, -1, -1], "o": 1304.0040372039202, "do": 1.6225129541742263, "d": 184.12145688274512, "dd": 2.0357142857142776, "s": 21.0, "ds": 0.0, "cap": 681, "dcap": 1, "st": 38, "dst": 0}, {"m": "Flagstore 1 (faulty) - checking service: Checker can't see the /dashboard in web application!\n", "c": 2, "dc": [2, 2, 2], "o": 1367.3519598673145, "do": 13.612918108419763, "d": 175.2419313217171, "dd": 0.0, "s": 177.0, "ds": 0.0, "cap": 633, "dcap": 5, "st": 0, "dst": 0}, {"m": "Flagstore 1 (faulty) - placing flag: Exception on connection (failed, timeout, did not give input, etc.)\n", "c": 2, "dc": [2, 2, 2], "o": 1394.3424112476239, "do": 5.942272202998765, "d": 24.352941176470594, "dd": 0.0, "s": 54.0, "ds": 0.0, "cap": 726, "dcap": 3, "st": 178, "dst": 0}, {"m": "Flagstore 1 (recovering) - checking flag: flag not found / not matching\n", "c": 4, "dc": [2, 4, 2], "o": 333.1908650269378, "do": 6.2480313515780495, "d": 65.09396392041857, "dd": 2.0344827586206904, "s": 88.5, "ds": 1.5, "cap": 162, "dcap": 3, "st": 81, "dst": 0}, {"m": "Flagstore 1 (faulty) - checking service: Checker can't register in web application!\n", "c": 2, "dc": [2, 0, 0], "o": 104.54579008073816, "do": 0.0, "d": 110.16998673399594, "dd": 0.0, "s": 78.0, "ds": 0.0, "cap": 38, "dcap": 0, "st": 2, "dst": 0}, {"m": "Flagstore 1 (up)\n", "c": 0, "dc": [2, 0, 0], "o": 335.83301396796196, "do": 6.3232963499399375, "d": 24.352941176470594, "dd": 0.0, "s": 24.0, "ds": 3.0, "cap": 166, "dcap": 3, "st": 45, "dst": 1}], "points": 5865.101298606315, "o": 4839.268077394497, "do": 33.74903096711074, "d": 583.333221211818, "dd": 4.070197044334968, "s": 442.5, "ds": 4.5}, {"rank": 5, "team_id": 27, "services": [{"m": "Flagstore 1 (faulty) - checking service: local variable 'order_id' referenced before assignment\n", "c": 2, "dc": [0, 2, 2], "o": 1141.1053723762147, "do": -0.03803418803408931, "d": 38.715476213896935, "dd": 0.0, "s": 105.0, "ds": 0.0, "cap": 569, "dcap": 0, "st": 516, "dst": 4}, {"m": "Flagstore 1 (faulty) - placing flag: list index out of range\n", "c": 2, "dc": [2, 0, 2], "o": 987.9250800237828, "do": 0.0, "d": 149.87900644868347, "dd": 0.0, "s": 222.0, "ds": 0.0, "cap": 481, "dcap": 0, "st": 17, "dst": 0}, {"m": "Flagstore 1 (faulty) - placing flag: Got EOF while expecting output: \"Operation:\"\n", "c": 2, "dc": [2, 2, 2], "o": 708.4087912493125, "do": 0.0, "d": 28.42223627802376, "dd": 0.0, "s": 99.0, "ds": 0.0, "cap": 369, "dcap": 0, "st": 366, "dst": 0}, {"m": "Flagstore 1 (faulty) - checking flag: Could not connect to service for getflag\n", "c": 2, "dc": [4, 2, 2], "o": 792.2567160732382, "do": -0.00909090909101451, "d": 109.85022339221194, "dd": 0.0011494252873518462, "s": 139.5, "ds": 0.0, "cap": 372, "dcap": 0, "st": 52, "dst": 0}, {"m": "Flagstore 1 (not checked)\n", "c": -1, "dc": [-1, -1, -1], "o": 0.0, "do": 0.0, "d": 132.440484142835, "dd": 2.0344827586206975, "s": 48.0, "ds": 0.0, "cap": 0, "dcap": 0, "st": 69, "dst": 0}, {"m": "Flagstore 1 (faulty) - checking service: Checker cannot login within the account!!\n", "c": 2, "dc": [2, 0, 2], "o": 717.3638848368089, "do": 3.8968175231151463, "d": 46.8974843228303, "dd": 0.0, "s": 207.0, "ds": 0.0, "cap": 358, "dcap": 2, "st": 87, "dst": 0}], "points": 5673.764755357838, "o": 4347.059844559357, "do": 3.8496924259900425, "d": 506.2049107984814, "dd": 2.0356321839080493, "s": 820.5, "ds": 0.0}, {"rank": 6, "team_id": 6, "services": [{"m": "Flagstore 1 (faulty) - checking service: Checker can not find the flight retrived by API using the ID!\n", "c": 2, "dc": [0, 2, 2], "o": 823.0824689221436, "do": 2.442857142857065, "d": 104.13110890547811, "dd": 0.0, "s": 180.0, "ds": 0.0, "cap": 424, "dcap": 1, "st": 102, "dst": 0}, {"m": "Flagstore 1 (up)\n", "c": 0, "dc": [-1, -1, 2], "o": 894.0183331614562, "do": -0.023809523809518396, "d": 44.73566503617869, "dd": 0.001231527093594309, "s": 207.0, "ds": 3.0, "cap": 463, "dcap": 0, "st": 270, "dst": 3}, {"m": "Flagstore 1 (faulty) - placing flag: Got EOF while expecting output: \"Operation:\"\n", "c": 2, "dc": [2, 2, 2], "o": 913.4782879444099, "do": 0.0, "d": 24.352941176470594, "dd": 0.0, "s": 102.0, "ds": 0.0, "cap": 476, "dcap": 0, "st": 373, "dst": 0}, {"m": "Flagstore 1 (faulty) - placing flag: Unhandled error at put flag. (Timeout?)\n", "c": 2, "dc": [4, 2, 2], "o": 192.49504336493953, "do": 6.275713012477695, "d": 101.68097738057466, "dd": 0.0011494252873518462, "s": 139.5, "ds": 0.0, "cap": 94, "dcap": 3, "st": 67, "dst": 0}, {"m": "Flagstore 1 (faulty) - placing flag: We cannot put the flag!!\n", "c": 2, "dc": [2, 2, 2], "o": 224.86491570713022, "do": 0.0, "d": 87.65965075371989, "dd": 0.0, "s": 48.0, "ds": 0.0, "cap": 103, "dcap": 0, "st": 21, "dst": 0}, {"m": "Flagstore 1 (faulty) - placing flag: HTTPSConnectionPool(host='172.16.6.5', port=443): \n", "c": 2, "dc": [2, 2, 2], "o": 815.4522616944766, "do": 4.734918253603382, "d": 34.592225619462134, "dd": 0.0, "s": 156.0, "ds": 0.0, "cap": 388, "dcap": 2, "st": 235, "dst": 0}], "points": 5093.04387966644, "o": 3863.3913107945564, "do": 13.429678885128624, "d": 397.15256887188406, "dd": 0.0023809523809461552, "s": 832.5, "ds": 3.0}, {"rank": 7, "team_id": 26, "services": [{"m": "Flagstore 1 (faulty) - checking service: Checker detects that LFD file can not be accesed!\n", "c": 2, "dc": [2, 0, 0], "o": 1171.4930245333917, "do": 3.9969650879688743, "d": 32.566820775132804, "dd": 0.0, "s": 168.0, "ds": 0.0, "cap": 599, "dcap": 2, "st": 499, "dst": 6}, {"m": "Flagstore 1 (faulty) - checking service: Checker can't see a client appointment in web application!\n", "c": 2, "dc": [2, 2, 2], "o": 763.759685561459, "do": 2.309523809523853, "d": 46.79790377782919, "dd": 0.0, "s": 204.0, "ds": 0.0, "cap": 387, "dcap": 1, "st": 230, "dst": 1}, {"m": "Flagstore 1 (faulty) - checking service: Exception on connection (failed, timeout, did not give input, etc.)\n", "c": 2, "dc": [2, 2, 2], "o": 1704.1656196568622, "do": 3.847981545559378, "d": 28.470588235294123, "dd": 0.0, "s": 111.0, "ds": 0.0, "cap": 876, "dcap": 2, "st": 199, "dst": 4}, {"m": "Flagstore 1 (recovering) - checking flag: flag not found / not matching\n", "c": 4, "dc": [4, 4, 2], "o": 0.0, "do": 0.0, "d": 79.37969578115042, "dd": 2.035632183908035, "s": 81.0, "ds": 1.5, "cap": 0, "dcap": 0, "st": 51, "dst": 0}, {"m": "Flagstore 1 (not checked)\n", "c": -1, "dc": [-1, -1, -1], "o": 26.47338111715274, "do": 0.0, "d": 130.47094318528596, "dd": 2.0344827586206975, "s": 108.0, "ds": 0.0, "cap": 12, "dcap": 0, "st": 38, "dst": 0}, {"m": "Flagstore 1 (faulty) - checking service: Checker cannot create account!!\n", "c": 2, "dc": [2, 2, 2], "o": 34.4659705058494, "do": 2.1421651013346548, "d": 30.52864782276548, "dd": 0.0, "s": 138.0, "ds": 0.0, "cap": 16, "dcap": 1, "st": 150, "dst": 3}], "points": 4858.572280952173, "o": 3700.357681374715, "do": 12.29663554438676, "d": 348.214599577458, "dd": 4.070114942528733, "s": 810.0, "ds": 1.5}, {"rank": 8, "team_id": 7, "services": [{"m": "Flagstore 1 (faulty) - checking service: Checker can not find the flight retrived by API using the ID!\n", "c": 2, "dc": [2, 2, 2], "o": 1014.2723451836538, "do": 3.6705027383228526, "d": 28.43641943734016, "dd": 0.0, "s": 108.0, "ds": 0.0, "cap": 508, "dcap": 2, "st": 328, "dst": 0}, {"m": "Flagstore 1 (faulty) - placing flag: list index out of range\n", "c": 2, "dc": [2, 2, 2], "o": 1869.555738355263, "do": -0.16666666666674246, "d": 115.38244466692377, "dd": 0.0, "s": 204.0, "ds": 0.0, "cap": 885, "dcap": 0, "st": 121, "dst": 0}, {"m": "Flagstore 1 (faulty) - checking service: Got EOF while expecting output: \"OK\"\n", "c": 2, "dc": [2, 2, 2], "o": 664.8268440718177, "do": 0.0, "d": 26.477941176470594, "dd": 0.0, "s": 102.0, "ds": 0.0, "cap": 340, "dcap": 0, "st": 390, "dst": 0}, {"m": "Flagstore 1 (faulty) - checking service: Could not upload file\n", "c": 2, "dc": [2, 2, 2], "o": 13.310899653979238, "do": 0.0, "d": 58.99426713669255, "dd": 0.0, "s": 87.0, "ds": 0.0, "cap": 6, "dcap": 0, "st": 66, "dst": 1}, {"m": "Flagstore 1 (faulty) - placing flag: We cannot put the flag!!\n", "c": 2, "dc": [-1, 2, 2], "o": 106.17277595530192, "do": 2.5, "d": 34.55743269530035, "dd": 0.0, "s": 3.0, "ds": 0.0, "cap": 47, "dcap": 1, "st": 9, "dst": 0}, {"m": "Flagstore 1 (up)\n", "c": 0, "dc": [0, 0, 0], "o": 2.0706947032206546, "do": -0.013986013986014179, "d": 30.46198879551821, "dd": 0.0, "s": 234.0, "ds": 3.0, "cap": 1, "dcap": 0, "st": 397, "dst": 7}], "points": 4702.5197918314825, "o": 3670.209297923236, "do": 5.989850057670096, "d": 294.31049390824563, "dd": 0.0, "s": 738.0, "ds": 3.0}, {"rank": 9, "team_id": 29, "services": [{"m": "Flagstore 1 (faulty) - checking service: Checker detects that LFD file can not be accesed!\n", "c": 2, "dc": [2, 2, -1], "o": 761.0157162038372, "do": 0.0, "d": 30.488801742919396, "dd": 0.0, "s": 27.0, "ds": 0.0, "cap": 390, "dcap": 0, "st": 182, "dst": 0}, {"m": "Flagstore 1 (not checked)\n", "c": -1, "dc": [2, 2, 2], "o": 48.1951346567696, "do": 0.0, "d": 44.94844464387809, "dd": 2.03846153846154, "s": 114.0, "ds": 0.0, "cap": 27, "dcap": 0, "st": 450, "dst": 0}, {"m": "Flagstore 1 (faulty) - placing flag: Received OK but flag was not updated at placeflag\n", "c": 2, "dc": [2, 2, 2], "o": 1312.9655381280347, "do": 2.4162629757786362, "d": 24.352941176470594, "dd": 0.0, "s": 93.0, "ds": 0.0, "cap": 673, "dcap": 1, "st": 357, "dst": 0}, {"m": "Flagstore 1 (up)\n", "c": 0, "dc": [0, 4, 4], "o": 259.03231287167273, "do": 4.208342945021144, "d": 85.50773819319753, "dd": 0.0, "s": 145.5, "ds": 3.0, "cap": 121, "dcap": 2, "st": 246, "dst": 11}, {"m": "Flagstore 1 (not checked)\n", "c": -1, "dc": [-1, -1, -1], "o": 11.126190476190477, "do": 0.0, "d": 79.31504573388402, "dd": 2.0344827586206833, "s": 75.0, "ds": 0.0, "cap": 5, "dcap": 0, "st": 51, "dst": 0}, {"m": "Flagstore 1 (faulty) - placing flag: Checker cannot create admin account for flag using public key!!\n", "c": 2, "dc": [2, 0, 2], "o": 1033.9805240415108, "do": 4.100689660205262, "d": 182.21845784173374, "dd": 0.0, "s": 231.0, "ds": 0.0, "cap": 488, "dcap": 2, "st": 0, "dst": 0}], "points": 4558.646845710098, "o": 3426.3154163780155, "do": 10.725295581005042, "d": 446.8314293320833, "dd": 4.072944297082223, "s": 685.5, "ds": 3.0}, {"rank": 10, "team_id": 11, "services": [{"m": "Flagstore 1 (faulty) - checking service: Checker detects that LFD file can not be accesed!\n", "c": 2, "dc": [2, 2, 2], "o": 900.3359731217125, "do": 3.7230978940322075, "d": 34.58935421994885, "dd": 0.0, "s": 15.0, "ds": 0.0, "cap": 451, "dcap": 2, "st": 6, "dst": 0}, {"m": "Flagstore 1 (faulty) - checking service: Checker can't see the /profile in web application!\n", "c": 2, "dc": [-1, 2, 2], "o": 786.6789593384315, "do": 6.956697973306973, "d": 42.74350576356276, "dd": -2.0344827586206904, "s": 204.0, "ds": 0.0, "cap": 398, "dcap": 3, "st": 231, "dst": 2}, {"m": "Flagstore 1 (up)\n", "c": 0, "dc": [2, 2, 0], "o": 972.1410434767233, "do": 2.05570934256059, "d": 63.802397588718996, "dd": 2.037037037037038, "s": 117.0, "ds": 3.0, "cap": 476, "dcap": 1, "st": 312, "dst": 0}, {"m": "Flagstore 1 (faulty) - placing flag: Could not get user token\n", "c": 2, "dc": [2, 2, 2], "o": 631.8203895105275, "do": 6.298550382719895, "d": 91.49495468041403, "dd": 0.0, "s": 148.5, "ds": 0.0, "cap": 287, "dcap": 3, "st": 148, "dst": 0}, {"m": "Flagstore 1 (not checked)\n", "c": -1, "dc": [-1, -1, -1], "o": 0.0, "do": 0.0, "d": 91.6215565323425, "dd": 2.0344827586206833, "s": 0.0, "ds": 0.0, "cap": 0, "dcap": 0, "st": 15, "dst": 0}, {"m": "Flagstore 1 (faulty) - placing flag: HTTPSConnectionPool(host='172.16.11.5', port=443):\n", "c": 2, "dc": [2, 2, 2], "o": 0.0, "do": 0.0, "d": 32.5270378385468, "dd": 0.0, "s": 162.0, "ds": 0.0, "cap": 0, "dcap": 0, "st": 253, "dst": 0}], "points": 4294.255172070929, "o": 3290.976365447395, "do": 19.034055592619666, "d": 356.7788066235339, "dd": 2.037037037037031, "s": 646.5, "ds": 3.0}, {"rank": 11, "team_id": 35, "services": [{"m": "Flagstore 1 (faulty) - placing flag: We cannot put the flag!!\n", "c": 2, "dc": [2, 2, -1], "o": 794.2453552688859, "do": 12.163475221433714, "d": 40.67845647437719, "dd": 0.0, "s": 189.0, "ds": 0.0, "cap": 391, "dcap": 6, "st": 571, "dst": 0}, {"m": "Flagstore 1 (faulty) - placing flag: list index out of range\n", "c": 2, "dc": [2, 2, 2], "o": 1354.870363503278, "do": 4.182764870654182, "d": 44.7716341395391, "dd": 0.0, "s": 207.0, "ds": 0.0, "cap": 645, "dcap": 2, "st": 408, "dst": 0}, {"m": "Flagstore 1 (faulty) - checking service: Server health bad\n", "c": 2, "dc": [2, 2, 2], "o": 818.3182799061498, "do": 4.033333333333303, "d": 24.352941176470594, "dd": 0.0, "s": 93.0, "ds": 0.0, "cap": 399, "dcap": 2, "st": 430, "dst": 0}, {"m": "Flagstore 1 (faulty) - checking flag: Could not connect to service for getflag\n", "c": 2, "dc": [4, 2, 2], "o": 0.0, "do": 0.0, "d": 40.60963105916854, "dd": -2.0333333333333314, "s": 112.5, "ds": 0.0, "cap": 0, "dcap": 0, "st": 276, "dst": 8}, {"m": "Flagstore 1 (faulty) - placing flag: We cannot put the flag!!\n", "c": 2, "dc": [-1, 2, -1], "o": 219.90548315582927, "do": 0.0, "d": 105.92560566701135, "dd": 0.0, "s": 30.0, "ds": 0.0, "cap": 92, "dcap": 0, "st": 33, "dst": 0}, {"m": "Flagstore 1 (faulty) - placing flag: HTTPSConnectionPool(host='172.16.35.5', port=443):\n", "c": 2, "dc": [2, 2, 2], "o": 0.0, "do": 0.0, "d": 36.70898692810458, "dd": 0.0, "s": 132.0, "ds": 0.0, "cap": 0, "dcap": 0, "st": 262, "dst": 2}], "points": 4243.8867372788145, "o": 3187.3394818341426, "do": 20.3795734254212, "d": 293.0472554446714, "dd": -2.0333333333333314, "s": 763.5, "ds": 0.0}, {"rank": 12, "team_id": 10, "services": [{"m": "Flagstore 1 (not checked)\n", "c": -1, "dc": [2, 2, 2], "o": 1209.7161821930797, "do": 4.447780708334449, "d": 32.51380038972111, "dd": 2.0357142857142847, "s": 81.0, "ds": 0.0, "cap": 590, "dcap": 2, "st": 60, "dst": 0}, {"m": "Flagstore 1 (not checked)\n", "c": -1, "dc": [2, 2, -1], "o": 1163.2159476720897, "do": -0.023809523809632083, "d": 115.26344025504456, "dd": 2.038461538461533, "s": 201.0, "ds": 0.0, "cap": 531, "dcap": 0, "st": 104, "dst": 0}, {"m": "Flagstore 1 (faulty) - placing flag: Got EOF while expecting output: \"Operation:\"\n", "c": 2, "dc": [2, 2, 2], "o": 82.97211837595147, "do": 4.041753171856982, "d": 26.477941176470594, "dd": 0.0, "s": 114.0, "ds": 0.0, "cap": 39, "dcap": 2, "st": 405, "dst": 0}, {"m": "Flagstore 1 (recovering) - checking flag: Flag was not placed successfully\n", "c": 4, "dc": [3, 4, 2], "o": 0.0, "do": 0.0, "d": 95.55849930309654, "dd": 2.0344827586206833, "s": 138.0, "ds": 1.5, "cap": 0, "dcap": 0, "st": 74, "dst": 0}, {"m": "Flagstore 1 (not checked)\n", "c": -1, "dc": [-1, -1, -1], "o": 4.365282583621684, "do": 0.0, "d": 69.13858195043728, "dd": 2.0344827586206833, "s": 0.0, "ds": 0.0, "cap": 2, "dcap": 0, "st": 79, "dst": 0}, {"m": "Flagstore 1 (faulty) - placing flag: Checker cannot create admin account for flag using public key!!\n", "c": 2, "dc": [2, 2, 2], "o": 424.51079375257564, "do": 4.154122040973277, "d": 30.54659197012139, "dd": 0.0, "s": 126.0, "ds": 0.0, "cap": 202, "dcap": 2, "st": 237, "dst": 0}], "points": 3914.27917962221, "o": 2884.7803245773184, "do": 12.619846397355076, "d": 369.49885504489146, "dd": 8.143141341417184, "s": 660.0, "ds": 1.5}, {"rank": 13, "team_id": 9, "services": [{"m": "Flagstore 1 (faulty) - placing flag: We cannot put the flag!!\n", "c": 2, "dc": [2, -1, 2], "o": 549.1704513425545, "do": 0.0, "d": 26.389978213507632, "dd": 0.0, "s": 3.0, "ds": 0.0, "cap": 274, "dcap": 0, "st": 71, "dst": 0}, {"m": "Flagstore 1 (faulty) - checking service: Checker can't see the /profile in web application!\n", "c": 2, "dc": [2, 2, 2], "o": 977.4222559783549, "do": 2.2994232987313126, "d": 156.68518209571081, "dd": 0.0, "s": 210.0, "ds": 0.0, "cap": 477, "dcap": 1, "st": 11, "dst": 0}, {"m": "Flagstore 1 (faulty) - placing flag: Got EOF while expecting output: \"Operation:\"\n", "c": 2, "dc": [2, 2, 2], "o": 414.3387833538624, "do": 2.0826989619376945, "d": 26.38865546218488, "dd": 0.0, "s": 75.0, "ds": 0.0, "cap": 207, "dcap": 1, "st": 339, "dst": 0}, {"m": "Flagstore 1 (faulty) - checking flag: Could not connect to service for getflag\n", "c": 2, "dc": [0, 0, 2], "o": 585.2867320011782, "do": 6.288131313131316, "d": 118.67539963349222, "dd": 0.0011494252873518462, "s": 150.0, "ds": 0.0, "cap": 270, "dcap": 3, "st": 45, "dst": 0}, {"m": "Flagstore 1 (faulty) - placing flag: We cannot put the flag!!\n", "c": 2, "dc": [-1, 2, 2], "o": 143.69035310133927, "do": 0.0, "d": 65.17414632625372, "dd": 0.0, "s": 0.0, "ds": 0.0, "cap": 66, "dcap": 0, "st": 47, "dst": 2}, {"m": "Flagstore 1 (faulty) - placing flag: Checker cannot login within the admin account for flag using public key!!\n", "c": 2, "dc": [2, 2, 2], "o": 0.0, "do": 0.0, "d": 36.68308195674295, "dd": 0.0, "s": 156.0, "ds": 0.0, "cap": 0, "dcap": 0, "st": 251, "dst": 0}], "points": 3693.905019465182, "o": 2669.908575777289, "do": 10.670253573800323, "d": 429.9964436878923, "dd": 0.0011494252873518462, "s": 594.0, "ds": 0.0}, {"rank": 14, "team_id": 3, "services": [{"m": "Flagstore 1 (faulty) - checking service: Checker can not find the  flightNumber on /get-flight-data!\n", "c": 2, "dc": [2, -1, 2], "o": 650.3319729119812, "do": 3.9286918963389326, "d": 28.4316448801743, "dd": 0.0, "s": 0.0, "ds": 0.0, "cap": 324, "dcap": 2, "st": 0, "dst": 0}, {"m": "Flagstore 1 (faulty) - placing flag: list index out of range\n", "c": 2, "dc": [2, 2, 2], "o": 1140.0050901472614, "do": -0.19047619047637454, "d": 48.98408375739413, "dd": 0.0, "s": 177.0, "ds": 0.0, "cap": 553, "dcap": 0, "st": 271, "dst": 0}, {"m": "Flagstore 1 (faulty) - placing flag: Got EOF while expecting output: \"Operation:\"\n", "c": 2, "dc": [2, 2, 2], "o": 994.4035291082433, "do": 0.0, "d": 24.352941176470594, "dd": 0.0, "s": 60.0, "ds": 0.0, "cap": 502, "dcap": 0, "st": 305, "dst": 0}, {"m": "Flagstore 1 (faulty) - checking service: Could not upload file\n", "c": 2, "dc": [2, 2, 2], "o": 0.0, "do": 0.0, "d": 26.384191176470594, "dd": 0.0, "s": 1.5, "ds": 0.0, "cap": 0, "dcap": 0, "st": 56, "dst": 1}, {"m": "Flagstore 1 (faulty) - placing flag: We cannot put the flag!!\n", "c": 2, "dc": [0, 2, 0], "o": 91.08199093294247, "do": 0.0, "d": 112.30426478679745, "dd": 0.0, "s": 168.0, "ds": 0.0, "cap": 41, "dcap": 0, "st": 20, "dst": 0}, {"m": "Flagstore 1 (faulty) - placing flag: Checker cannot create admin account for flag using public key!!\n", "c": 2, "dc": [2, 2, 2], "o": 0.0, "do": 0.0, "d": 24.352941176470594, "dd": 0.0, "s": 93.0, "ds": 0.0, "cap": 0, "dcap": 0, "st": 177, "dst": 0}], "points": 3640.1326500542064, "o": 2875.8225831004283, "do": 3.738215705862558, "d": 264.81006695377766, "dd": 0.0, "s": 499.5, "ds": 0.0}, {"rank": 15, "team_id": 24, "services": [{"m": "Flagstore 1 (not checked)\n", "c": -1, "dc": [-1, -1, -1], "o": 57.172896665692384, "do": 0.0, "d": 46.780011307461265, "dd": 2.0357142857142847, "s": 93.0, "ds": 0.0, "cap": 29, "dcap": 0, "st": 415, "dst": 0}, {"m": "Flagstore 1 (faulty) - checking service: Checker can't see a client appointment edit page within the web application!\n", "c": 2, "dc": [2, 2, -1], "o": 157.81700546185834, "do": 0.0, "d": 139.9713895353774, "dd": 0.0, "s": 198.0, "ds": 0.0, "cap": 76, "dcap": 0, "st": 22, "dst": 0}, {"m": "Flagstore 1 (faulty) - placing flag: Was not asked for operation\n", "c": 2, "dc": [2, 2, 2], "o": 294.97396939199706, "do": 0.0, "d": 24.352941176470594, "dd": 0.0, "s": 96.0, "ds": 0.0, "cap": 148, "dcap": 0, "st": 404, "dst": 0}, {"m": "Flagstore 1 (recovering) - checking flag: Flag was not placed successfully\n", "c": 4, "dc": [4, 4, 2], "o": 0.0, "do": 0.0, "d": 73.23810694533745, "dd": 2.035632183908035, "s": 66.0, "ds": 1.5, "cap": 0, "dcap": 0, "st": 58, "dst": 0}, {"m": "Flagstore 1 (not checked)\n", "c": -1, "dc": [-1, -1, -1], "o": 0.0, "do": 0.0, "d": 81.38943435695684, "dd": 2.0344827586206833, "s": 24.0, "ds": 0.0, "cap": 0, "dcap": 0, "st": 60, "dst": 0}, {"m": "Flagstore 1 (faulty) - placing flag: Checker cannot create admin account for flag using public key!!\n", "c": 2, "dc": [2, 2, 2], "o": 1633.5094915561176, "do": 0.0, "d": 65.53213954947704, "dd": 0.0, "s": 147.0, "ds": 0.0, "cap": 718, "dcap": 0, "st": 108, "dst": 0}], "points": 3198.737385946746, "o": 2143.4733630756655, "do": 0.0, "d": 431.2640228710806, "dd": 6.105829228243003, "s": 624.0, "ds": 1.5}, {"rank": 16, "team_id": 21, "services": [{"m": "Flagstore 1 (faulty) - placing flag: We cannot put the flag!!\n", "c": 2, "dc": [-1, 2, 2], "o": 51.706292186494466, "do": 0.0, "d": 26.387423935091284, "dd": 0.0, "s": 6.0, "ds": 0.0, "cap": 27, "dcap": 0, "st": 100, "dst": 0}, {"m": "Flagstore 1 (up)\n", "c": 0, "dc": [-1, 0, 0], "o": 101.47017465425769, "do": 0.0, "d": 168.77284780099163, "dd": 2.0396930655551273, "s": 222.0, "ds": 3.0, "cap": 49, "dcap": 0, "st": 9, "dst": 0}, {"m": "Flagstore 1 (faulty) - placing flag: Got EOF while expecting output: \"Operation:\"\n", "c": 2, "dc": [2, 2, 2], "o": 787.7711765886844, "do": 2.0993079584775387, "d": 26.477941176470594, "dd": 0.0, "s": 78.0, "ds": 0.0, "cap": 398, "dcap": 1, "st": 322, "dst": 0}, {"m": "Flagstore 1 (faulty) - placing flag: Could not get user token\n", "c": 2, "dc": [2, 4, 4], "o": 487.58168798713785, "do": 13.174242424242436, "d": 85.93254672598022, "dd": 0.0, "s": 141.0, "ds": 0.0, "cap": 190, "dcap": 5, "st": 79, "dst": 0}, {"m": "Flagstore 1 (up)\n", "c": 0, "dc": [-1, 0, 0], "o": 2.333333333333333, "do": 0.0, "d": 101.85694123996879, "dd": 2.0344827586206833, "s": 63.0, "ds": 3.0, "cap": 1, "dcap": 0, "st": 0, "dst": 0}, {"m": "Flagstore 1 (up)\n", "c": 0, "dc": [2, 2, 0], "o": 183.52708268279196, "do": 2.1288711288711113, "d": 36.73315212049733, "dd": 0.0, "s": 228.0, "ds": 3.0, "cap": 86, "dcap": 1, "st": 398, "dst": 2}], "points": 2798.5506004317, "o": 1614.3897474326996, "do": 17.402421511591086, "d": 446.1608529989998, "dd": 4.074175824175811, "s": 738.0, "ds": 9.0}, {"rank": 17, "team_id": 22, "services": [{"m": "Flagstore 1 (faulty) - placing flag: We cannot put the flag!!\n", "c": 2, "dc": [-1, -1, 2], "o": 326.82328437098647, "do": 0.0, "d": 28.424460972128323, "dd": 0.0, "s": 30.0, "ds": 0.0, "cap": 161, "dcap": 0, "st": 226, "dst": 0}, {"m": "Flagstore 1 (faulty) - placing flag: list index out of range\n", "c": 2, "dc": [-1, 2, -1], "o": 223.66501482466012, "do": 0.0, "d": 42.80102301790281, "dd": 0.001231527093594309, "s": 168.0, "ds": 0.0, "cap": 109, "dcap": 0, "st": 244, "dst": 0}, {"m": "Flagstore 1 (faulty) - placing flag: Got EOF while expecting output: \"Operation:\"\n", "c": 2, "dc": [2, 2, 2], "o": 860.3629388144137, "do": 0.0, "d": 26.477941176470594, "dd": 0.0, "s": 93.0, "ds": 0.0, "cap": 425, "dcap": 0, "st": 330, "dst": 0}, {"m": "Flagstore 1 (faulty) - placing flag: place flag did not succeed\n", "c": 2, "dc": [2, 2, 2], "o": 0.0, "do": 0.0, "d": 24.352941176470594, "dd": 0.0, "s": 0.0, "ds": 0.0, "cap": 0, "dcap": 0, "st": 36, "dst": 0}, {"m": "Flagstore 1 (up)\n", "c": 0, "dc": [-1, 2, -1], "o": 489.3571016641953, "do": 0.0, "d": 116.03575146937231, "dd": 0.0, "s": 120.0, "ds": 3.0, "cap": 198, "dcap": 0, "st": 190, "dst": 2}, {"m": "Flagstore 1 (faulty) - placing flag: We cannot put the flag!!\n", "c": 2, "dc": [2, 2, 2], "o": 142.87766004660472, "do": 0.0, "d": 30.563792824822244, "dd": 0.0, "s": 54.0, "ds": 0.0, "cap": 69, "dcap": 0, "st": 82, "dst": 0}], "points": 2776.741910358027, "o": 2043.0859997208602, "do": 0.0, "d": 268.65591063716687, "dd": 0.001231527093594309, "s": 465.0, "ds": 3.0}, {"rank": 18, "team_id": 13, "services": [{"m": "Flagstore 1 (faulty) - checking service: Checker detects that LFD file can not be accesed!\n", "c": 2, "dc": [2, 2, 2], "o": 265.1688196608412, "do": 8.055723073543106, "d": 38.668231606652334, "dd": 0.0, "s": 63.0, "ds": 0.0, "cap": 131, "dcap": 4, "st": 112, "dst": 2}, {"m": "Flagstore 1 (faulty) - placing flag: list index out of range\n", "c": 2, "dc": [2, 2, 2], "o": 2.1659746251441754, "do": 0.0, "d": 40.79267411904985, "dd": 0.0, "s": 207.0, "ds": 0.0, "cap": 1, "dcap": 0, "st": 269, "dst": 0}, {"m": "Flagstore 1 (up)\n", "c": 0, "dc": [0, 2, 2], "o": 1013.3037166834499, "do": 0.0, "d": 24.352941176470594, "dd": 0.0, "s": 132.0, "ds": 3.0, "cap": 504, "dcap": 0, "st": 501, "dst": 10}, {"m": "Flagstore 1 (faulty) - placing flag: Could not get user token\n", "c": 2, "dc": [2, 2, 2], "o": 4.637889273356402, "do": 0.0, "d": 24.352941176470594, "dd": 0.0, "s": 0.0, "ds": 0.0, "cap": 2, "dcap": 0, "st": 0, "dst": 0}, {"m": "Flagstore 1 (faulty) - placing flag: We cannot put the flag!!\n", "c": 2, "dc": [2, 2, 2], "o": 233.16519619365644, "do": 2.5, "d": 36.58427538833873, "dd": 0.0, "s": 6.0, "ds": 0.0, "cap": 102, "dcap": 1, "st": 175, "dst": 0}, {"m": "Flagstore 1 (faulty) - placing flag: HTTPSConnectionPool(host='172.16.13.5', port=443):\n", "c": 2, "dc": [2, 2, 2], "o": 474.832958948011, "do": 0.0, "d": 28.424736048265466, "dd": 0.0, "s": 12.0, "ds": 0.0, "cap": 214, "dcap": 0, "st": 375, "dst": 0}], "points": 2606.4503548997063, "o": 1993.2745553844593, "do": 10.555723073543106, "d": 193.17579951524758, "dd": 0.0, "s": 420.0, "ds": 3.0}, {"rank": 19, "team_id": 14, "services": [{"m": "Flagstore 1 (not checked)\n", "c": -1, "dc": [-1, -1, -1], "o": 0.0, "do": 0.0, "d": 59.034582685739736, "dd": 2.0357142857142847, "s": 102.0, "ds": 0.0, "cap": 0, "dcap": 0, "st": 642, "dst": 0}, {"m": "Flagstore 1 (faulty) - placing flag: We cannot put the flag!!\n", "c": 2, "dc": [2, 2, 2], "o": 0.0, "do": 0.0, "d": 30.456188503855856, "dd": 0.0, "s": 204.0, "ds": 0.0, "cap": 0, "dcap": 0, "st": 388, "dst": 0}, {"m": "Flagstore 1 (faulty) - placing flag: Got EOF while expecting output: \"Operation:\"\n", "c": 2, "dc": [2, 2, 2], "o": 849.4659081002961, "do": 2.0974625144175434, "d": 24.352941176470594, "dd": 0.0, "s": 111.0, "ds": 0.0, "cap": 431, "dcap": 1, "st": 419, "dst": 0}, {"m": "Flagstore 1 (faulty) - checking service: incorrect status code\n", "c": 2, "dc": [2, 2, 2], "o": 0.0, "do": 0.0, "d": 32.476108331895816, "dd": 0.0, "s": 10.5, "ds": 0.0, "cap": 0, "dcap": 0, "st": 42, "dst": 0}, {"m": "Flagstore 1 (up)\n", "c": 0, "dc": [2, 0, -1], "o": 23.819830400280225, "do": 0.0, "d": 65.16861215811214, "dd": 0.0, "s": 108.0, "ds": 3.0, "cap": 11, "dcap": 0, "st": 54, "dst": 1}, {"m": "Flagstore 1 (faulty) - placing flag: Checker cannot create admin account for flag using public key!!\n", "c": 2, "dc": [2, 2, 2], "o": 741.3175349160643, "do": 4.206852125191176, "d": 36.71161850705195, "dd": 0.0, "s": 54.0, "ds": 0.0, "cap": 345, "dcap": 2, "st": 27, "dst": 0}], "points": 2452.3033247797666, "o": 1614.6032734166406, "do": 6.3043146396087195, "d": 248.2000513631261, "dd": 2.0357142857142847, "s": 589.5, "ds": 3.0}, {"rank": 20, "team_id": 15, "services": [{"m": "Flagstore 1 (faulty) - placing flag: We cannot put the flag!!\n", "c": 2, "dc": [2, 2, 2], "o": 316.4544111335169, "do": -0.0047619047618923105, "d": 28.428655462184878, "dd": 0.0, "s": 51.0, "ds": 0.0, "cap": 152, "dcap": 0, "st": 205, "dst": 0}, {"m": "Flagstore 1 (faulty) - checking service: local variable 'app_id' referenced before assignment\n", "c": 2, "dc": [2, 0, 2], "o": 29.288426207587108, "do": 0.0, "d": 30.445805301592785, "dd": 0.0, "s": 201.0, "ds": 0.0, "cap": 14, "dcap": 0, "st": 459, "dst": 3}, {"m": "Flagstore 1 (faulty) - checking service: Got EOF while expecting output: \"Operation:\"\n", "c": 2, "dc": [2, 2, 2], "o": 67.21572859666286, "do": 0.0, "d": 24.352941176470594, "dd": 0.0, "s": 90.0, "ds": 0.0, "cap": 31, "dcap": 0, "st": 413, "dst": 2}, {"m": "Flagstore 1 (recovering) - checking flag: flag not found / not matching\n", "c": 4, "dc": [4, 2, 2], "o": 55.68999423298732, "do": 0.0, "d": 97.604512436501, "dd": 2.035632183908035, "s": 138.0, "ds": 1.5, "cap": 24, "dcap": 0, "st": 78, "dst": 0}, {"m": "Flagstore 1 (faulty) - checking service: Checker can't add the custom location by API in web application!\n", "c": 2, "dc": [-1, 2, 2], "o": 146.38870875376065, "do": 0.0, "d": 36.60342425427753, "dd": 0.0, "s": 6.0, "ds": 0.0, "cap": 65, "dcap": 0, "st": 83, "dst": 1}, {"m": "Flagstore 1 (up)\n", "c": 0, "dc": [0, 0, 0], "o": 1017.2934175589886, "do": 4.628871128871083, "d": 26.41176470588236, "dd": 0.0, "s": 84.0, "ds": 3.0, "cap": 465, "dcap": 2, "st": 143, "dst": 12}], "points": 2446.1777898204127, "o": 1632.3306864835035, "do": 4.624109224109191, "d": 243.8471033369091, "dd": 2.035632183908035, "s": 570.0, "ds": 4.5}, {"rank": 21, "team_id": 34, "services": [{"m": "Flagstore 1 (faulty) - checking service: Checker can not see the recently API added flight when searched by id!\n", "c": 2, "dc": [2, 0, 0], "o": 469.85747357713416, "do": -0.010256410256374693, "d": 67.22120404844055, "dd": 0.0, "s": 123.0, "ds": 0.0, "cap": 225, "dcap": 0, "st": 343, "dst": 3}, {"m": "Flagstore 1 (faulty) - checking service: Checker can't see the /clients in web application!\n", "c": 2, "dc": [2, 2, 2], "o": 47.88244785299283, "do": 0.0, "d": 69.5465073968473, "dd": 0.0, "s": 120.0, "ds": 0.0, "cap": 23, "dcap": 0, "st": 288, "dst": 2}, {"m": "Flagstore 1 (faulty) - placing flag: Got EOF while expecting output: \"Operation:\"\n", "c": 2, "dc": [2, 2, 2], "o": 107.4951924821302, "do": 0.0, "d": 24.352941176470594, "dd": 0.0, "s": 72.0, "ds": 0.0, "cap": 49, "dcap": 0, "st": 324, "dst": 0}, {"m": "Flagstore 1 (faulty) - placing flag: Could not get user token\n", "c": 2, "dc": [2, 2, 2], "o": 2.125, "do": 0.0, "d": 128.64340579496914, "dd": 0.0, "s": 144.0, "ds": 0.0, "cap": 1, "dcap": 0, "st": 0, "dst": 0}, {"m": "Flagstore 1 (faulty) - placing flag: We cannot put the flag!!\n", "c": 2, "dc": [2, 2, 2], "o": 48.60967259384215, "do": 0.0, "d": 99.74588492576139, "dd": 0.0, "s": 9.0, "ds": 0.0, "cap": 22, "dcap": 0, "st": 32, "dst": 0}, {"m": "Flagstore 1 (faulty) - placing flag: We cannot put the flag!!\n", "c": 2, "dc": [2, 2, 2], "o": 744.5830834966647, "do": 4.1844266844267395, "d": 24.352941176470594, "dd": 0.0, "s": 24.0, "ds": 0.0, "cap": 347, "dcap": 2, "st": 40, "dst": 0}], "points": 2326.4157545217236, "o": 1420.552870002764, "do": 4.174170274170365, "d": 413.8628845189596, "dd": 0.0, "s": 492.0, "ds": 0.0}, {"rank": 22, "team_id": 2, "services": [{"m": "Flagstore 1 (faulty) - checking service: Checker detects that LFD file can not be accesed!\n", "c": 2, "dc": [-1, 2, 0], "o": 382.67003859624043, "do": 9.087161166399824, "d": 139.4325461532385, "dd": 0.0, "s": 24.0, "ds": 0.0, "cap": 181, "dcap": 4, "st": 11, "dst": 0}, {"m": "Flagstore 1 (faulty) - checking service: Checker can't see a client appointment by ID within the web application!\n", "c": 2, "dc": [2, 2, 2], "o": 108.52069139530218, "do": 0.0, "d": 30.484393632060982, "dd": 0.0, "s": 207.0, "ds": 0.0, "cap": 51, "dcap": 0, "st": 375, "dst": 2}, {"m": "Flagstore 1 (faulty) - placing flag: Got EOF while expecting output: \"Operation:\"\n", "c": 2, "dc": [2, 2, 2], "o": 586.2404327985686, "do": 0.0, "d": 24.352941176470594, "dd": 0.0, "s": 111.0, "ds": 0.0, "cap": 286, "dcap": 0, "st": 424, "dst": 0}, {"m": "Flagstore 1 (recovering) - checking flag: flag not found / not matching\n", "c": 4, "dc": [4, 2, 4], "o": 181.5600856563659, "do": 6.299242424242436, "d": 91.57708321918047, "dd": 2.035632183908035, "s": 139.5, "ds": 1.5, "cap": 85, "dcap": 3, "st": 126, "dst": 0}, {"m": "Flagstore 1 (faulty) - placing flag: We cannot put the flag!!\n", "c": 2, "dc": [-1, -1, -1], "o": 82.10538440797954, "do": 0.0, "d": 54.87730299940027, "dd": 0.0, "s": 36.0, "ds": 0.0, "cap": 37, "dcap": 0, "st": 84, "dst": 0}, {"m": "Flagstore 1 (faulty) - placing flag: HTTPSConnectionPool(host='172.16.2.5', port=443): \n", "c": 2, "dc": [2, 2, 2], "o": 0.0, "do": 0.0, "d": 28.455572755417965, "dd": 0.0, "s": 66.0, "ds": 0.0, "cap": 0, "dcap": 0, "st": 75, "dst": 0}], "points": 2293.7764727902254, "o": 1341.0966328544566, "do": 15.38640359064226, "d": 369.17983993576877, "dd": 2.035632183908035, "s": 583.5, "ds": 1.5}, {"rank": 23, "team_id": 18, "services": [{"m": "Flagstore 1 (faulty) - placing flag: We cannot put the flag!!\n", "c": 2, "dc": [2, 2, 2], "o": 683.6265379700149, "do": 0.0, "d": 38.635638438950465, "dd": 0.0, "s": 75.0, "ds": 0.0, "cap": 334, "dcap": 0, "st": 123, "dst": 0}, {"m": "Flagstore 1 (faulty) - placing flag: list index out of range\n", "c": 2, "dc": [2, 2, -1], "o": 0.0, "do": 0.0, "d": 36.667150489278306, "dd": 0.0, "s": 93.0, "ds": 0.0, "cap": 0, "dcap": 0, "st": 202, "dst": 0}, {"m": "Flagstore 1 (flag not found) - checking flag: Flag missmatch for current tick\n", "c": 3, "dc": [2, 2, 2], "o": 895.550608393538, "do": 0.0, "d": 24.352941176470594, "dd": 0.0, "s": 102.0, "ds": 0.0, "cap": 444, "dcap": 0, "st": 401, "dst": 1}, {"m": "Flagstore 1 (faulty) - checking service: incorrect status code\n", "c": 2, "dc": [2, 2, 2], "o": 0.0, "do": 0.0, "d": 26.477941176470594, "dd": 0.0, "s": 6.0, "ds": 0.0, "cap": 0, "dcap": 0, "st": 73, "dst": 0}, {"m": "Flagstore 1 (not checked)\n", "c": -1, "dc": [-1, -1, -1], "o": 21.775143541579524, "do": 0.0, "d": 81.39351699921825, "dd": 2.0344827586206833, "s": 66.0, "ds": 0.0, "cap": 10, "dcap": 0, "st": 113, "dst": 0}, {"m": "Flagstore 1 (faulty) - placing flag: Checker cannot create admin account for flag using public key!!\n", "c": 2, "dc": [2, 2, 2], "o": 0.0, "do": 0.0, "d": 26.40849673202615, "dd": 0.0, "s": 105.0, "ds": 0.0, "cap": 0, "dcap": 0, "st": 240, "dst": 0}], "points": 2281.8879749175467, "o": 1600.9522899051324, "do": 0.0, "d": 233.93568501241435, "dd": 2.0344827586206833, "s": 447.0, "ds": 0.0}, {"rank": 24, "team_id": 33, "services": [{"m": "Flagstore 1 (not checked)\n", "c": -1, "dc": [-1, -1, -1], "o": 441.5571461851773, "do": 0.0, "d": 112.10959997161522, "dd": 2.035714285714292, "s": 60.0, "ds": 0.0, "cap": 213, "dcap": 0, "st": 44, "dst": 0}, {"m": "Flagstore 1 (not checked)\n", "c": -1, "dc": [-1, -1, -1], "o": 185.3748228703246, "do": 0.0, "d": 104.22320526545133, "dd": 2.0396930655551415, "s": 171.0, "ds": 0.0, "cap": 85, "dcap": 0, "st": 134, "dst": 0}, {"m": "Flagstore 1 (faulty) - placing flag: Got EOF while expecting output: \"Operation:\"\n", "c": 2, "dc": [2, 2, 2], "o": 487.4502934329142, "do": 0.0, "d": 24.352941176470594, "dd": 0.0, "s": 99.0, "ds": 0.0, "cap": 239, "dcap": 0, "st": 408, "dst": 0}, {"m": "Flagstore 1 (faulty) - placing flag: Could not get user token\n", "c": 2, "dc": [2, 2, 2], "o": 0.0, "do": 0.0, "d": 142.8402218015432, "dd": 0.0, "s": 159.0, "ds": 0.0, "cap": 0, "dcap": 0, "st": 0, "dst": 0}, {"m": "Flagstore 1 (not checked)\n", "c": -1, "dc": [-1, -1, -1], "o": 53.36185582007382, "do": 0.0, "d": 95.67807494605114, "dd": 2.0344827586206833, "s": 27.0, "ds": 0.0, "cap": 24, "dcap": 0, "st": 18, "dst": 0}, {"m": "Flagstore 1 (faulty) - placing flag: HTTPSConnectionPool(host='172.16.33.5', port=443):\n", "c": 2, "dc": [2, 2, 2], "o": 0.0, "do": 0.0, "d": 28.44641943734016, "dd": 0.0, "s": 66.0, "ds": 0.0, "cap": 0, "dcap": 0, "st": 60, "dst": 0}], "points": 2257.3945809069614, "o": 1167.7441183084898, "do": 0.0, "d": 507.65046259847173, "dd": 6.109890109890117, "s": 582.0, "ds": 0.0}, {"rank": 25, "team_id": 4, "services": [{"m": "Flagstore 1 (not checked)\n", "c": -1, "dc": [-1, -1, -1], "o": 555.0983787576544, "do": 0.0, "d": 54.955484781131666, "dd": 2.0357142857142847, "s": 3.0, "ds": 0.0, "cap": 266, "dcap": 0, "st": 79, "dst": 0}, {"m": "Flagstore 1 (not checked)\n", "c": -1, "dc": [-1, -1, -1], "o": 4.103798364265493, "do": 0.0, "d": 55.00533244737446, "dd": 2.0396930655551344, "s": 12.0, "ds": 0.0, "cap": 2, "dcap": 0, "st": 24, "dst": 0}, {"m": "Flagstore 1 (faulty) - placing flag: Was not asked for operation\n", "c": 2, "dc": [2, 2, 2], "o": 881.1570838728786, "do": 0.0, "d": 24.352941176470594, "dd": 0.0, "s": 93.0, "ds": 0.0, "cap": 431, "dcap": 0, "st": 354, "dst": 0}, {"m": "Flagstore 1 (faulty) - placing flag: Could not get user token\n", "c": 2, "dc": [2, 2, 2], "o": 0.0, "do": 0.0, "d": 73.18196508591974, "dd": 0.0, "s": 109.5, "ds": 0.0, "cap": 0, "dcap": 0, "st": 65, "dst": 0}, {"m": "Flagstore 1 (not checked)\n", "c": -1, "dc": [-1, -1, -1], "o": 0.0, "do": 0.0, "d": 52.81405125763072, "dd": 2.0344827586206904, "s": 0.0, "ds": 0.0, "cap": 0, "dcap": 0, "st": 28, "dst": 0}, {"m": "Flagstore 1 (faulty) - placing flag: HTTPSConnectionPool(host='172.16.4.5', port=443): \n", "c": 2, "dc": [2, 2, 2], "o": 0.0, "do": 0.0, "d": 24.352941176470594, "dd": 0.0, "s": 0.0, "ds": 0.0, "cap": 0, "dcap": 0, "st": 0, "dst": 0}], "points": 1942.521976919796, "o": 1440.3592609947984, "do": 0.0, "d": 284.66271592499777, "dd": 6.1098901098901095, "s": 217.5, "ds": 0.0}, {"rank": 26, "team_id": 12, "services": [{"m": "Flagstore 1 (not checked)\n", "c": -1, "dc": [2, 2, 2], "o": 22.777512769813807, "do": 0.0, "d": 30.486741586586795, "dd": 2.0357142857142847, "s": 147.0, "ds": 0.0, "cap": 11, "dcap": 0, "st": 889, "dst": 4}, {"m": "Flagstore 1 (up)\n", "c": 0, "dc": [-1, 2, -1], "o": 110.57850072841421, "do": 0.0, "d": 44.790028319953734, "dd": 0.001231527093594309, "s": 216.0, "ds": 3.0, "cap": 53, "dcap": 0, "st": 306, "dst": 1}, {"m": "Flagstore 1 (faulty) - placing flag: Got EOF while expecting output: \"Operation:\"\n", "c": 2, "dc": [2, 2, 2], "o": 614.4892600339288, "do": 0.0, "d": 34.938655462184876, "dd": 0.0, "s": 78.0, "ds": 0.0, "cap": 299, "dcap": 0, "st": 113, "dst": 0}, {"m": "Flagstore 1 (faulty) - placing flag: place flag did not succeed\n", "c": 2, "dc": [2, 2, 2], "o": 129.87131959735765, "do": 6.299242424242408, "d": 24.352941176470594, "dd": 0.0, "s": 0.0, "ds": 0.0, "cap": 62, "dcap": 3, "st": 59, "dst": 0}, {"m": "Flagstore 1 (not checked)\n", "c": -1, "dc": [2, 2, 2], "o": 0.0, "do": 0.0, "d": 30.457135473552825, "dd": 2.0344827586206904, "s": 3.0, "ds": 0.0, "cap": 0, "dcap": 0, "st": 27, "dst": 0}, {"m": "Flagstore 1 (faulty) - placing flag: Checker cannot create admin account for flag using public key!!\n", "c": 2, "dc": [2, 2, 2], "o": 0.0, "do": 0.0, "d": 30.499383753501405, "dd": 0.0, "s": 162.0, "ds": 0.0, "cap": 0, "dcap": 0, "st": 300, "dst": 0}], "points": 1679.2414789017648, "o": 877.7165931295144, "do": 6.299242424242408, "d": 195.52488577225023, "dd": 4.071428571428569, "s": 606.0, "ds": 3.0}, {"rank": 27, "team_id": 8, "services": [{"m": "Flagstore 1 (faulty) - checking service: Checker detects that LFD file can not be accesed!\n", "c": 2, "dc": [2, 2, 2], "o": 303.474993949829, "do": 0.0, "d": 28.46112831097352, "dd": 0.0, "s": 24.0, "ds": 0.0, "cap": 147, "dcap": 0, "st": 527, "dst": 4}, {"m": "Flagstore 1 (faulty) - placing flag: We cannot put the flag!!\n", "c": 2, "dc": [2, 2, 2], "o": 0.0, "do": 0.0, "d": 28.46986425339367, "dd": 0.0, "s": 87.0, "ds": 0.0, "cap": 0, "dcap": 0, "st": 333, "dst": 0}, {"m": "Flagstore 1 (faulty) - placing flag: Got EOF while expecting output: \"Operation:\"\n", "c": 2, "dc": [3, 2, 2], "o": 614.9673520032235, "do": 0.0, "d": 24.352941176470594, "dd": 0.0, "s": 96.0, "ds": 0.0, "cap": 299, "dcap": 0, "st": 400, "dst": 0}, {"m": "Flagstore 1 (flag not found) - checking flag: flag not found / not matching\n", "c": 3, "dc": [2, 4, 4], "o": 0.0, "do": 0.0, "d": 34.53700711053653, "dd": 0.0, "s": 19.5, "ds": 0.0, "cap": 0, "dcap": 0, "st": 128, "dst": 0}, {"m": "Flagstore 1 (faulty) - placing flag: We cannot put the flag!!\n", "c": 2, "dc": [0, 0, -1], "o": 49.46588411588413, "do": 0.0, "d": 79.32316673666001, "dd": 0.0, "s": 159.0, "ds": 0.0, "cap": 23, "dcap": 0, "st": 69, "dst": 0}, {"m": "Flagstore 1 (faulty) - placing flag: HTTPSConnectionPool(host='172.16.8.5', port=443): \n", "c": 2, "dc": [2, 2, 2], "o": 0.0, "do": 0.0, "d": 26.41176470588236, "dd": 0.0, "s": 30.0, "ds": 0.0, "cap": 0, "dcap": 0, "st": 45, "dst": 0}], "points": 1604.9641023628533, "o": 967.9082300689366, "do": 0.0, "d": 221.55587229391668, "dd": 0.0, "s": 415.5, "ds": 0.0}, {"rank": 28, "team_id": 20, "services": [{"m": "Flagstore 1 (up)\n", "c": 0, "dc": [0, 0, 2], "o": 108.78430282447519, "do": 0.0, "d": 38.641419437340154, "dd": 0.0, "s": 60.0, "ds": 3.0, "cap": 50, "dcap": 0, "st": 513, "dst": 14}, {"m": "Flagstore 1 (faulty) - placing flag: list index out of range\n", "c": 2, "dc": [2, 2, 2], "o": 18.638369963369964, "do": 0.0, "d": 34.6363017429194, "dd": 0.0, "s": 0.0, "ds": 0.0, "cap": 9, "dcap": 0, "st": 0, "dst": 0}, {"m": "Flagstore 1 (faulty) - checking service: Server health bad\n", "c": 2, "dc": [2, 2, 2], "o": 266.3304331877586, "do": 0.0, "d": 24.352941176470594, "dd": 0.0, "s": 96.0, "ds": 0.0, "cap": 130, "dcap": 0, "st": 439, "dst": 1}, {"m": "Flagstore 1 (recovering) - checking flag: flag not found / not matching\n", "c": 4, "dc": [2, 4, 4], "o": 12.904761904761905, "do": 0.0, "d": 71.1866615876048, "dd": 2.0344827586206833, "s": 55.5, "ds": 1.5, "cap": 6, "dcap": 0, "st": 77, "dst": 0}, {"m": "Flagstore 1 (up)\n", "c": 0, "dc": [-1, 2, 2], "o": 113.46158008658006, "do": 2.5, "d": 65.05814838485772, "dd": 2.0344827586206833, "s": 69.0, "ds": 3.0, "cap": 47, "dcap": 1, "st": 101, "dst": 0}, {"m": "Flagstore 1 (faulty) - placing flag: HTTPSConnectionPool(host='172.16.20.5', port=443):\n", "c": 2, "dc": [2, 2, 2], "o": 289.3068216577732, "do": 4.374902874902887, "d": 28.48210784313726, "dd": 0.0, "s": 141.0, "ds": 0.0, "cap": 128, "dcap": 2, "st": 272, "dst": 0}], "points": 1493.2838497970488, "o": 809.4262696247189, "do": 6.874902874902887, "d": 262.35758017232996, "dd": 4.068965517241367, "s": 421.5, "ds": 7.5}, {"rank": 29, "team_id": 5, "services": [{"m": "Flagstore 1 (faulty) - placing flag: We cannot put the flag!!\n", "c": 2, "dc": [2, 2, -1], "o": 594.725781472723, "do": 4.3306526806526335, "d": 26.389978213507632, "dd": 0.0, "s": 78.0, "ds": 0.0, "cap": 275, "dcap": 2, "st": 358, "dst": 0}, {"m": "Flagstore 1 (faulty) - placing flag: We cannot put the flag!!\n", "c": 2, "dc": [0, 2, 0], "o": 35.59230183983644, "do": 0.0, "d": 28.508496732026153, "dd": 0.0, "s": 135.0, "ds": 0.0, "cap": 17, "dcap": 0, "st": 353, "dst": 1}, {"m": "Flagstore 1 (up)\n", "c": 0, "dc": [2, 2, 0], "o": 8.86111111111111, "do": 0.0, "d": 26.477941176470594, "dd": 0.0, "s": 93.0, "ds": 3.0, "cap": 4, "dcap": 0, "st": 419, "dst": 6}, {"m": "Flagstore 1 (recovering) - checking flag: flag not found / not matching\n", "c": 4, "dc": [4, 4, 2], "o": 0.0, "do": 0.0, "d": 77.33093779903038, "dd": 2.035632183908035, "s": 63.0, "ds": 1.5, "cap": 0, "dcap": 0, "st": 82, "dst": 0}, {"m": "Flagstore 1 (not checked)\n", "c": -1, "dc": [-1, -1, -1], "o": 0.0, "do": 0.0, "d": 77.25443446956567, "dd": 2.0344827586206833, "s": 15.0, "ds": 0.0, "cap": 0, "dcap": 0, "st": 12, "dst": 0}, {"m": "Flagstore 1 (faulty) - placing flag: HTTPSConnectionPool(host='172.16.5.5', port=443): \n", "c": 2, "dc": [2, 2, 2], "o": 0.0, "do": 0.0, "d": 24.352941176470594, "dd": 0.0, "s": 0.0, "ds": 0.0, "cap": 0, "dcap": 0, "st": 17, "dst": 0}], "points": 1283.4939239907415, "o": 639.1791944236705, "do": 4.3306526806526335, "d": 260.314729567071, "dd": 4.070114942528718, "s": 384.0, "ds": 4.5}, {"rank": 30, "team_id": 30, "services": [{"m": "Flagstore 1 (not checked)\n", "c": -1, "dc": [2, 2, 2], "o": 0.0, "do": 0.0, "d": 26.38865546218488, "dd": 2.0357142857142847, "s": 3.0, "ds": 0.0, "cap": 0, "dcap": 0, "st": 5, "dst": 0}, {"m": "Flagstore 1 (faulty) - placing flag: We cannot put the flag!!\n", "c": 2, "dc": [2, 2, -1], "o": 65.57445224901973, "do": 0.0, "d": 59.24589713954646, "dd": 0.0, "s": 174.0, "ds": 0.0, "cap": 31, "dcap": 0, "st": 398, "dst": 1}, {"m": "Flagstore 1 (faulty) - placing flag: Got EOF while expecting output: \"Operation:\"\n", "c": 2, "dc": [2, 2, 2], "o": 331.337454328654, "do": 0.0, "d": 32.491127638794985, "dd": 0.0, "s": 102.0, "ds": 0.0, "cap": 161, "dcap": 0, "st": 373, "dst": 0}, {"m": "Flagstore 1 (recovering) - checking flag: flag not found / not matching\n", "c": 4, "dc": [4, 4, 2], "o": 0.0, "do": 0.0, "d": 77.39104308275242, "dd": 2.035632183908035, "s": 147.0, "ds": 1.5, "cap": 0, "dcap": 0, "st": 260, "dst": 0}, {"m": "Flagstore 1 (faulty) - placing flag: We cannot put the flag!!\n", "c": 2, "dc": [-1, 2, 2], "o": 0.0, "do": 0.0, "d": 73.51630592179956, "dd": 0.0, "s": 60.0, "ds": 0.0, "cap": 0, "dcap": 0, "st": 6, "dst": 0}, {"m": "Flagstore 1 (faulty) - placing flag: Checker cannot create admin account for flag using public key!!\n", "c": 2, "dc": [2, 2, 2], "o": 0.0, "do": 0.0, "d": 30.532324293353714, "dd": 0.0, "s": 57.0, "ds": 0.0, "cap": 0, "dcap": 0, "st": 37, "dst": 0}], "points": 1239.4772601161055, "o": 396.91190657767373, "do": 0.0, "d": 299.565353538432, "dd": 4.07134646962232, "s": 543.0, "ds": 1.5}, {"rank": 31, "team_id": 25, "services": [{"m": "Flagstore 1 (not checked)\n", "c": -1, "dc": [-1, -1, -1], "o": 68.52099214020767, "do": 0.0, "d": 40.653054785722134, "dd": 2.0357142857142847, "s": 15.0, "ds": 0.0, "cap": 33, "dcap": 0, "st": 820, "dst": 0}, {"m": "Flagstore 1 (faulty) - placing flag: We cannot put the flag!!\n", "c": 2, "dc": [2, 2, 2], "o": 0.0, "do": 0.0, "d": 45.07474618305821, "dd": 0.0, "s": 48.0, "ds": 0.0, "cap": 0, "dcap": 0, "st": 176, "dst": 0}, {"m": "Flagstore 1 (faulty) - placing flag: Got EOF while expecting output: \"Operation:\"\n", "c": 2, "dc": [2, 2, 2], "o": 452.5507652780908, "do": 0.0, "d": 24.352941176470594, "dd": 0.0, "s": 78.0, "ds": 0.0, "cap": 219, "dcap": 0, "st": 346, "dst": 0}, {"m": "Flagstore 1 (faulty) - checking service: Cannot read PDF title from path\n", "c": 2, "dc": [2, 2, 2], "o": 0.0, "do": 0.0, "d": 46.79252247330996, "dd": 0.0, "s": 57.0, "ds": 0.0, "cap": 0, "dcap": 0, "st": 35, "dst": 0}, {"m": "Flagstore 1 (faulty) - placing flag: We cannot put the flag!!\n", "c": 2, "dc": [2, 0, 0], "o": 0.0, "do": 0.0, "d": 95.64239198254768, "dd": 0.0, "s": 69.0, "ds": 0.0, "cap": 0, "dcap": 0, "st": 69, "dst": 0}, {"m": "Flagstore 1 (faulty) - placing flag: Checker cannot login within the admin account for flag using public key!!\n", "c": 2, "dc": [2, 2, 2], "o": 90.27013521849163, "do": 2.07692307692308, "d": 24.352941176470594, "dd": 0.0, "s": 18.0, "ds": 0.0, "cap": 42, "dcap": 1, "st": 29, "dst": 0}], "points": 1173.2104904143694, "o": 611.3418926367901, "do": 2.07692307692308, "d": 276.86859777757917, "dd": 2.0357142857142847, "s": 285.0, "ds": 0.0}, {"rank": 32, "team_id": 17, "services": [{"m": "Flagstore 1 (not checked)\n", "c": -1, "dc": [-1, -1, -1], "o": 0.0, "do": 0.0, "d": 40.653054785722134, "dd": 2.0357142857142847, "s": 0.0, "ds": 0.0, "cap": 0, "dcap": 0, "st": 0, "dst": 0}, {"m": "Flagstore 1 (not checked)\n", "c": -1, "dc": [-1, -1, -1], "o": 0.0, "do": 0.0, "d": 46.83735456459108, "dd": 2.0396930655551344, "s": 171.0, "ds": 0.0, "cap": 0, "dcap": 0, "st": 406, "dst": 0}, {"m": "Flagstore 1 (faulty) - placing flag: Was not asked for operation\n", "c": 2, "dc": [2, 2, 2], "o": 0.0, "do": 0.0, "d": 24.352941176470594, "dd": 0.0, "s": 90.0, "ds": 0.0, "cap": 0, "dcap": 0, "st": 424, "dst": 0}, {"m": "Flagstore 1 (faulty) - placing flag: Could not get user token\n", "c": 2, "dc": [2, 2, 2], "o": 0.0, "do": 0.0, "d": 85.4142745080959, "dd": 0.0, "s": 115.5, "ds": 0.0, "cap": 0, "dcap": 0, "st": 66, "dst": 0}, {"m": "Flagstore 1 (not checked)\n", "c": -1, "dc": [-1, -1, -1], "o": 0.0, "do": 0.0, "d": 46.72785530628878, "dd": 2.0344827586206904, "s": 3.0, "ds": 0.0, "cap": 0, "dcap": 0, "st": 34, "dst": 0}, {"m": "Flagstore 1 (faulty) - placing flag: HTTPSConnectionPool(host='172.16.17.5', port=443):\n", "c": 2, "dc": [2, 2, 2], "o": 0.0, "do": 0.0, "d": 36.63687910838807, "dd": 0.0, "s": 78.0, "ds": 0.0, "cap": 0, "dcap": 0, "st": 82, "dst": 0}], "points": 738.1223594495566, "o": 0.0, "do": 0.0, "d": 280.62235944955654, "dd": 6.1098901098901095, "s": 457.5, "ds": 0.0}, {"rank": 33, "team_id": 32, "services": [{"m": "Flagstore 1 (faulty) - placing flag: We cannot put the flag!!\n", "c": 2, "dc": [2, 2, 2], "o": 0.0, "do": 0.0, "d": 26.424369747899167, "dd": 0.0, "s": 0.0, "ds": 0.0, "cap": 0, "dcap": 0, "st": 0, "dst": 0}, {"m": "Flagstore 1 (faulty) - placing flag: We cannot put the flag!!\n", "c": 2, "dc": [-1, 0, 2], "o": 83.39575424575423, "do": 0.0, "d": 34.56366885458958, "dd": 0.001231527093594309, "s": 105.0, "ds": 0.0, "cap": 39, "dcap": 0, "st": 379, "dst": 0}, {"m": "Flagstore 1 (faulty) - placing flag: Got EOF while expecting output: \"Operation:\"\n", "c": 2, "dc": [2, 2, 2], "o": 0.0, "do": 0.0, "d": 24.352941176470594, "dd": 0.0, "s": 99.0, "ds": 0.0, "cap": 0, "dcap": 0, "st": 417, "dst": 0}, {"m": "Flagstore 1 (faulty) - placing flag: Could not get user token\n", "c": 2, "dc": [2, 2, 2], "o": 0.0, "do": 0.0, "d": 24.352941176470594, "dd": 0.0, "s": 0.0, "ds": 0.0, "cap": 0, "dcap": 0, "st": 0, "dst": 0}, {"m": "Flagstore 1 (not checked)\n", "c": -1, "dc": [-1, -1, -1], "o": 0.0, "do": 0.0, "d": 56.88557105328845, "dd": 2.0344827586206904, "s": 0.0, "ds": 0.0, "cap": 0, "dcap": 0, "st": 43, "dst": 0}, {"m": "Flagstore 1 (faulty) - placing flag: Checker cannot create admin account for flag using public key!!\n", "c": 2, "dc": [2, 2, 2], "o": 0.0, "do": 0.0, "d": 24.352941176470594, "dd": 0.0, "s": 18.0, "ds": 0.0, "cap": 0, "dcap": 0, "st": 65, "dst": 0}], "points": 496.3281874309433, "o": 83.39575424575423, "do": 0.0, "d": 190.93243318518898, "dd": 2.0357142857142847, "s": 222.0, "ds": 0.0}, {"rank": 34, "team_id": 31, "services": [{"m": "Flagstore 1 (faulty) - placing flag: We cannot put the flag!!\n", "c": 2, "dc": [2, 2, 2], "o": 0.0, "do": 0.0, "d": 24.352941176470594, "dd": 0.0, "s": 60.0, "ds": 0.0, "cap": 0, "dcap": 0, "st": 470, "dst": 0}, {"m": "Flagstore 1 (faulty) - placing flag: list index out of range\n", "c": 2, "dc": [2, 2, 2], "o": 0.0, "do": 0.0, "d": 26.424369747899167, "dd": 0.0, "s": 0.0, "ds": 0.0, "cap": 0, "dcap": 0, "st": 0, "dst": 0}, {"m": "Flagstore 1 (faulty) - checking service: Got EOF while expecting output: \"Operation:\"\n", "c": 2, "dc": [2, 2, 0], "o": 0.0, "do": 0.0, "d": 24.352941176470594, "dd": 0.0, "s": 96.0, "ds": 0.0, "cap": 0, "dcap": 0, "st": 385, "dst": 3}, {"m": "Flagstore 1 (faulty) - placing flag: Could not get user token\n", "c": 2, "dc": [2, 2, 2], "o": 0.0, "do": 0.0, "d": 24.352941176470594, "dd": 0.0, "s": 0.0, "ds": 0.0, "cap": 0, "dcap": 0, "st": 0, "dst": 0}, {"m": "Flagstore 1 (faulty) - placing flag: We cannot put the flag!!\n", "c": 2, "dc": [2, 2, 2], "o": 0.0, "do": 0.0, "d": 124.38805246173487, "dd": 0.0, "s": 3.0, "ds": 0.0, "cap": 0, "dcap": 0, "st": 21, "dst": 0}, {"m": "Flagstore 1 (faulty) - placing flag: Checker cannot create admin account for flag using public key!!\n", "c": 2, "dc": [2, 2, 2], "o": 0.0, "do": 0.0, "d": 24.352941176470594, "dd": 0.0, "s": 0.0, "ds": 0.0, "cap": 0, "dcap": 0, "st": 0, "dst": 0}], "points": 407.2241869155164, "o": 0.0, "do": 0.0, "d": 248.22418691551644, "dd": 0.0, "s": 159.0, "ds": 0.0}], "status-descriptions": {"0": "up", "1": "down", "2": "faulty", "3": "flag not found", "4": "recovering", "-1": "not checked"}, "services": [{"name": "airport", "first_blood": [27], "attackers": 13, "victims": 7}, {"name": "crm", "first_blood": [9], "attackers": 6, "victims": 9}, {"name": "jassem", "first_blood": [23], "attackers": 12, "victims": 7}, {"name": "media-library", "first_blood": [9], "attackers": 11, "victims": 6}, {"name": "pymap", "first_blood": [28], "attackers": 6, "victims": 5}, {"name": "spotify", "first_blood": [24], "attackers": 14, "victims": 6}]}